{
  "openapi": "3.0.1",
  "info": {
    "title": "LibraryManagementProj.API",
    "version": "1.0"
  },
  "paths": {
    "/api/Book": {
      "post": {
        "tags": [
          "Book"
        ],
        "requestBody": {
          "content": {
            "application/json": {
              "schema": {
                "$ref": "#/components/schemas/CreateOrUpdateBookDto"
              }
            },
            "text/json": {
              "schema": {
                "$ref": "#/components/schemas/CreateOrUpdateBookDto"
              }
            },
            "application/*+json": {
              "schema": {
                "$ref": "#/components/schemas/CreateOrUpdateBookDto"
              }
            }
          }
        },
        "responses": {
          "200": {
            "description": "OK"
          }
        }
      }
    },
    "/api/Book/{id}": {
      "put": {
        "tags": [
          "Book"
        ],
        "parameters": [
          {
            "name": "id",
            "in": "path",
            "required": true,
            "schema": {
              "type": "integer",
              "format": "int32"
            }
          }
        ],
        "requestBody": {
          "content": {
            "application/json": {
              "schema": {
                "$ref": "#/components/schemas/CreateOrUpdateBookDto"
              }
            },
            "text/json": {
              "schema": {
                "$ref": "#/components/schemas/CreateOrUpdateBookDto"
              }
            },
            "application/*+json": {
              "schema": {
                "$ref": "#/components/schemas/CreateOrUpdateBookDto"
              }
            }
          }
        },
        "responses": {
          "200": {
            "description": "OK"
          }
        }
      },
      "delete": {
        "tags": [
          "Book"
        ],
        "parameters": [
          {
            "name": "id",
            "in": "path",
            "required": true,
            "schema": {
              "type": "integer",
              "format": "int32"
            }
          }
        ],
        "responses": {
          "200": {
            "description": "OK"
          }
        }
      }
    }
  },
  "components": {
    "schemas": {
      "CreateOrUpdateBookDto": {
        "type": "object",
        "properties": {
          "bookName": {
            "type": "string",
            "nullable": true
          },
          "description": {
            "type": "string",
            "nullable": true
          },
          "publicationDate": {
            "type": "string",
            "format": "date-time"
          },
          "authorName": {
            "type": "string",
            "nullable": true
          },
          "pages": {
            "type": "integer",
            "format": "int32"
          },
          "quantity": {
            "type": "integer",
            "format": "int32"
          }
        },
        "additionalProperties": false
      }
    }
  }
}